carculator_two_wheeler/__init__.py
carculator_two_wheeler/inventory.py
carculator_two_wheeler/model.py
carculator_two_wheeler/two_wheelers_input_parameters.py
carculator_two_wheeler/data/default_parameters.json
carculator_two_wheeler/data/extra_parameters.json
carculator_two_wheeler-0.1.0.dist-info/LICENSE
carculator_two_wheeler-0.1.0.dist-info/METADATA
carculator_two_wheeler-0.1.0.dist-info/WHEEL
carculator_two_wheeler-0.1.0.dist-info/top_level.txt
carculator_two_wheeler-0.1.0.dist-info/RECORD
